DTRGym/__init__.py
DTRGym/ahn_chemo_env.py
DTRGym/base.py
DTRGym/ghaffari_cancer_env.py
DTRGym/simglucose_env.py
DTRGym/utils.py
DTRGym/OberstSepsisEnv/DataGenerator.py
DTRGym/OberstSepsisEnv/MDP.py
DTRGym/OberstSepsisEnv/__init__.py
DTRGym/OberstSepsisEnv/action.py
DTRGym/OberstSepsisEnv/env.py
DTRGym/OberstSepsisEnv/generate_data.py
DTRGym/OberstSepsisEnv/learn_transition.py
DTRGym/OberstSepsisEnv/policy.py
DTRGym/OberstSepsisEnv/state.py
DTRGym/OberstSepsisEnv/cf/__init__.py
DTRGym/OberstSepsisEnv/cf/counterfactual.py
DTRGym/OberstSepsisEnv/cf/gumbelTools.py
DTRGym/OberstSepsisEnv/cf/utils.py
DTRGym/OberstSepsisEnv/mdptoolboxSrc/__init__.py
DTRGym/OberstSepsisEnv/mdptoolboxSrc/error.py
DTRGym/OberstSepsisEnv/mdptoolboxSrc/example.py
DTRGym/OberstSepsisEnv/mdptoolboxSrc/mdp.py
DTRGym/OberstSepsisEnv/mdptoolboxSrc/util.py
DTRGym-0.1.0.dist-info/LICENSE
DTRGym-0.1.0.dist-info/METADATA
DTRGym-0.1.0.dist-info/WHEEL
DTRGym-0.1.0.dist-info/top_level.txt
DTRGym-0.1.0.dist-info/RECORD
