Metadata-Version: 2.1
Name: DTRGym
Version: 0.1.0
Summary: A Collection of Reinforcement Learning Environments for Dynamic Treatment Regime Simulation.
Home-page: http://github.com/GilesLuo/DTRGym
Author: Zhiyao Luo, Mingcheng Zhu
Author-email: zhiyao.luo@eng.ox.ac.uk
License: MIT
Project-URL: Source Code, https://github.com/GilesLuo/DTRGym
Keywords: Healthcare Simulation,Dynamic Treatment Regime,Reinforcement Learning
Requires-Python: == 3.10.*
License-File: LICENSE
Requires-Dist: torch >=1.13
Requires-Dist: numpy ==1.25.*
Requires-Dist: tianshou ==0.5.0
Requires-Dist: simglucose ==0.2.3
Requires-Dist: urllib3
Requires-Dist: packaging
Requires-Dist: tqdm
Requires-Dist: matplotlib
Requires-Dist: scipy
Requires-Dist: pandas
Requires-Dist: gymnasium
Requires-Dist: gym
Provides-Extra: dev
Requires-Dist: flake8 ; extra == 'dev'
Requires-Dist: pytest ; extra == 'dev'
Requires-Dist: pytest-cov ; extra == 'dev'
Requires-Dist: mypy ; extra == 'dev'
